memtab_visualizers/__init__.py
memtab_visualizers/category_memmap_report.py
memtab_visualizers/excel_report.py
memtab_visualizers/memmap_report.py
memtab_visualizers/memory_profiler_report.py
memtab_visualizers/ram_treemap_report.py
memtab_visualizers/summary_report.py
memtab_visualizers/treemap_report.py
memtab_visualizers-1.0.1.dist-info/METADATA
memtab_visualizers-1.0.1.dist-info/WHEEL
memtab_visualizers-1.0.1.dist-info/entry_points.txt
memtab_visualizers-1.0.1.dist-info/licenses/LICENSE.md
memtab_visualizers-1.0.1.dist-info/RECORD
