Metadata-Version: 2.4
Name: memtab-visualizers
Version: 1.0.1
Summary: Utility to be paired with memtab to visualize the output
Project-URL: Bug Tracker, https://github.com/etn-corp/memtab-visualizers/issues
License-File: LICENSE.md
Classifier: Development Status :: 4 - Beta
Classifier: Environment :: Console
Classifier: Intended Audience :: Developers
Classifier: License :: OSI Approved :: MIT License
Classifier: Topic :: Software Development :: Build Tools
Classifier: Topic :: Software Development :: Embedded Systems
Requires-Python: >=3.9
Requires-Dist: kaleido!=0.2.1.post1,>=0.2.0; sys_platform != 'win32'
Requires-Dist: kaleido==0.1.0.post1; sys_platform == 'win32'
Requires-Dist: memtab>=0.11.0
Requires-Dist: plotly>=6.0.1
